multi_cycle/mem.v
module mem(input         clk, we,
           input  [31:0] a, wd,
           output  [31:0] rd);

  reg  [31:0] RAM[63:0];

  // initialize memory with instructions
  initial
    begin
      $readmemh("ehm.dat",RAM);  // "memfile.dat" contains your instructions in hex
                                     // you must create this file
    end

  assign rd = RAM[a[31:2]]; // word aligned

  always@(posedge clk)
    if (we)
      RAM[a[31:2]] <= wd;
endmodule

multi_cycle/mipsparts.v
module regfile(input        clk, 
               input          we3, 
               input   [4:0]  ra1, ra2, wa3, 
               input   [31:0] wd3, 
               output  [31:0] rd1, rd2);

  reg [31:0] rf[31:0];



  always @(posedge clk)
    if (we3) rf[wa3] <= wd3;	

  assign rd1 = (ra1 != 0) ? rf[ra1] : 0;
  assign rd2 = (ra2 != 0) ? rf[ra2] : 0;
endmodule


module adder(input  [31:0] a, b,
             output [31:0] y);

  assign y = a + b;
endmodule


module sl2(input  [31:0] a,
           output [31:0] y);

  // shift left by 2
  assign y = {a[29:0], 2'b00};
endmodule

module signext(input  [15:0] a,
               output [31:0] y);
              
  assign y = {{16{a[15]}}, a};
endmodule



module flopr #(parameter WIDTH = 8)
              (input            clk, reset,
               input  [WIDTH-1:0] d, 
               output reg  [WIDTH-1:0] q);

  always@(posedge clk, posedge reset)
    if (reset) q <= 0;
    else       q <= d;
endmodule





module flopenr #(parameter WIDTH = 8)
                (input               clk, reset,
                 input               en,
                 input   [WIDTH-1:0] d, 
                 output reg [WIDTH-1:0] q);
 
  always@(posedge clk, posedge reset)
    if      (reset) q <= 0;
    else if (en)    q <= d;
endmodule




module mux2 #(parameter WIDTH = 8)
             (input  [WIDTH-1:0] d0, d1, 
              input   s, 
              output  [WIDTH-1:0] y);

  assign y = s ? d1 : d0; 
endmodule






module mux3 #(parameter WIDTH = 8)
             (input [WIDTH-1:0] d0, d1, d2,
              input [1:0]       s, 
              output [WIDTH-1:0] y);

  assign #1 y = s[1] ? d2 : (s[0] ? d1 : d0); 
endmodule





module mux4 #(parameter WIDTH = 8)
             (input   [WIDTH-1:0] d0, d1, d2, d3,
              input   [1:0]       s, 
              output  reg [WIDTH-1:0] y);

   always @(*)
      case(s)
         2'b00: y <= d0;
         2'b01: y <= d1;
         2'b10: y <= d2;
         2'b11: y <= d3;
      endcase
endmodule

multi_cycle/Alu.v
module alu(a,b,aluop,result,zero);
input [31:0] a,b;
input [2:0] aluop;
output reg [31:0] result; 
output reg zero;

always @(*)
begin
    case (aluop)
        3'b010: //ADD
        begin
           result <= a + b; 
           zero <= 1'b0;
        end 
        3'b110: //SUB
        begin
           result <= a - b; 
           zero <= 1'b0;            
        end 
        3'b000: //AND
        begin
           result <= a & b; 
           zero <= 1'b0;
        end 
        3'b001: //OR
        begin
           result <= a | b; 
           zero <= 1'b0;
        end 
        3'b111: //SLT
        begin
           result <= (a < b) ? 1:0; 
           zero <= 1'b0;  
        end
        3'b100: //BEQ 
        begin
           result <= 32'dx; 
           zero <= (a==b) ? 1'b1:1'b0;
        end 
         3'b100: //BEQ 
        begin
           result <= 32'dx; 
           zero <= (a!=b) ? 1'b1:1'b0;
        end
    endcase
end 
endmodule

multi_cycle/datapath.v
`include "mipsparts.v"
`include "Alu.v"
module datapath(input          clk, reset,
                input          pcen, irwrite, regwrite,
                input          alusrca, iord, memtoreg, regdst,
                input   [1:0]  alusrcb, pcsrc, 
                input   [2:0]  alucontrol,
                output  [5:0]  op, funct,
                output         zero,
                output  [31:0] adr, writedata, 
                input   [31:0] readdata);

  // Below are the internal signals of the datapath module.

  wire [4:0]  writereg;
  wire [31:0] pcnext, pc;
  wire [31:0] instr, data, srca, srcb;
  wire [31:0] a;
  wire [31:0] aluresult, aluout;
  wire [31:0] signimm;   // the sign-extended immediate
  wire [31:0] signimmsh;	// the sign-extended immediate shifted left by 2
  wire [31:0] wd3, rd1, rd2;

  // op and funct fields to controller
  assign op = instr[31:26];
  assign funct = instr[5:0];

  // Your datapath hardware goes below.  Instantiate each of the submodules
  // that you need.  Remember that alu's, mux's and various other 
  // versions of parameterizable modules are available in mipsparts.sv
  // from Lab 9. You'll likely want to include this verilog file in your
  // simulation.

  // We've included parameterizable 3:1 and 4:1 muxes below for your use.

  // Remember to give your instantiated modules applicable names
  // such as pcreg (PC register), wdmux (Write Data Mux), etc.
  // so it's easier to understand.


  // datapath


  flopenr #(32) pcreg(clk, reset, pcen, pcnext, pc);
  mux2    #(32) adrmux(pc, aluout, iord, adr);
  flopenr #(32) instrreg(clk, reset, irwrite, readdata, instr);
  flopr   #(32) datareg(clk, reset, readdata, data);
  mux2    #(5)  regdstmux(instr[20:16], instr[15:11],regdst, writereg);
  mux2    #(32) wdmux(aluout, data, memtoreg, wd3);
  regfile       rf(clk, regwrite, instr[25:21], instr[20:16], writereg, wd3, rd1, rd2);
  signext       se(instr[15:0], signimm);
  //assign zeroimm = {16'b0, instr[15:0]}; // !!!DANGER!!!
  //mux2    #(32) orimux(zeroimm, signimm, ori, immcomplete);
  sl2           immsh(signimm, signimmsh);
  flopr   #(32) areg(clk, reset, rd1, a);
  flopr   #(32) breg(clk, reset, rd2, writedata);
  mux2    #(32) srcamux(pc, a, alusrca, srca);
  //mux4    #(32) srcbmux(writedata, 32'b100, immcomplete, signimmsh, alusrcb, srcb);
  mux4    #(32) srcbmux(writedata, 32'b100, signimm, signimmsh, alusrcb, srcb);
  alu           alu(srca, srcb, alucontrol, aluresult, zero);
  flopr   #(32) alureg(clk, reset, aluresult, aluout);
  mux3    #(32) pcmux(aluresult, aluout, {pc[31:28], instr[25:0], 2'b00}, pcsrc, pcnext);  
endmodule

multi_cycle/aludec.v
module aludec(input  logic [5:0] funct,
              input  logic [1:0] aluop,
              output logic [2:0] alucontrol);

  // ADD CODE HERE
  // Complete the design for the ALU Decoder.
  // Your design goes here.  Remember that this is a combinational 
  // module. 

  // Remember that you may also reuse any code from previous labs.
  always @(*)
    case(aluop)
      2'b00: alucontrol <= 3'b010;  // add
      2'b01: alucontrol <= 3'b110;  // sub
      2'b11: alucontrol <= 3'b001;   // or
	// falta beq
      default: case(funct)          // RTYPE
          6'b100000: alucontrol <= 3'b010; // ADD
          6'b100010: alucontrol <= 3'b110; // SUB
          6'b100100: alucontrol <= 3'b000; // AND
          6'b100101: alucontrol <= 3'b001; // OR
          6'b101010: alucontrol <= 3'b111; // SLT
          default:   alucontrol <= 3'bxxx; 
        endcase
  endcase

endmodule

multi_cycle/maindec.v
module maindec(input   clk, reset, 
               input   [5:0] op, 
               output        pcwrite, memwrite, irwrite, regwrite,
               output        alusrca, branch, iord, memtoreg, regdst,
               output [1:0] alusrcb, pcsrc,
               output [1:0] aluop);

  parameter   FETCH   = 4'b0000; // State 0
  parameter   DECODE  = 4'b0001; // State 1
  parameter   MEMADR  = 4'b0010;	// State 2
  parameter   MEMRD   = 4'b0011;	// State 3
  parameter   MEMWB   = 4'b0100;	// State 4
  parameter   MEMWR   = 4'b0101;	// State 5
  parameter   RTYPEEX = 4'b0110;	// State 6
  parameter   RTYPEWB = 4'b0111;	// State 7
  parameter   BEQEX   = 4'b1000;	// State 8
  parameter   ADDIEX  = 4'b1001;	// State 9
  parameter   ADDIWB  = 4'b1010;	// state 10
  parameter   JEX     = 4'b1011;	// State 11

  parameter   LW      = 6'b100011;	// Opcode for lw
  parameter   SW      = 6'b101011;	// Opcode for sw
  parameter   RTYPE   = 6'b000000;	// Opcode for R-type
  parameter   BEQ     = 6'b000100;	// Opcode for beq
  parameter   ADDI    = 6'b001000;	// Opcode for addi
  parameter   J       = 6'b000010;	// Opcode for j

  logic [3:0]  state, nextstate;
  logic [14:0] controls;

  // state register
  always @(posedge clk or posedge reset)			
    if(reset) state <= FETCH;
    else state <= nextstate;

  // ADD CODE HERE
  // Finish entering the next state logic below.  We've completed the first 
  // two states, FETCH and DECODE, for you.

  // next state logic
  always @(*)
    case(state)
      FETCH:   nextstate <= DECODE;
      DECODE:  case(op)
                 LW:      nextstate <= MEMADR;
                 SW:      nextstate <= MEMADR;
                 RTYPE:   nextstate <= RTYPEEX;
                 BEQ:     nextstate <= BEQEX;
                 ADDI:    nextstate <= ADDIEX;
                 J:       nextstate <= JEX;
                 default: nextstate <= 4'bx; // should never happen
               endcase
 		// Add code here
      MEMADR:  case(op)
                 LW:      nextstate <= MEMRD;
                 SW:      nextstate <= MEMWR;
                 default: nextstate <= 4'bx;
               endcase
      MEMRD: nextstate <= MEMWB;
      MEMWB: nextstate <= FETCH;
      MEMWR: nextstate <= FETCH;
      RTYPEEX: nextstate <= RTYPEWB;
      RTYPEWB: nextstate <= FETCH;
      BEQEX:   nextstate <= FETCH;
      ADDIEX:  nextstate <= ADDIWB;
      ADDIWB:  nextstate <= FETCH;
      JEX: nextstate <= FETCH;    
      default: nextstate <= 4'bx; // should never happen
    endcase

  // output logic
  assign {pcwrite, memwrite, irwrite, regwrite, 
          alusrca, branch, iord, memtoreg, regdst,
          alusrcb, pcsrc, aluop} = controls;

  // ADD CODE HERE
  // Finish entering the output logic below.  We've entered the
  // output logic for the first two states, S0 and S1, for you.
  always @(*)
    case(state)
      FETCH:   controls <= 15'h5010;
      DECODE:  controls <= 15'h0030;
    // your code goes here 
      MEMADR:  controls <= 15'h0420;      
      MEMRD:   controls <= 15'h0100;
      MEMWB:   controls <= 15'h0880;
      MEMWR:   controls <= 15'h2100;
      RTYPEEX: controls <= 15'h0402;
      RTYPEWB: controls <= 15'h0840;
      BEQEX:   controls <= 15'h0605;
      ADDIEX:  controls <= 15'h0420;
      ADDIWB:  controls <= 15'h0800;
      JEX:     controls <= 15'h4008;
      		
	 
      default: controls <= 15'hxxxx; // should never happen
    endcase
endmodule

multi_cycle/controller.v

`include "maindec.v"
`include "aludec.v"
module controller(input         clk, reset,
                  input [5:0] op, funct,
                  input      zero,
                  output      pcen, memwrite, irwrite, regwrite,
                  output       alusrca, iord, memtoreg, regdst,
                  output [1:0] alusrcb, pcsrc,
                  output [2:0] alucontrol);

  wire [1:0] aluop;
  wire       branch, pcwrite;

  // Main Decoder and ALU Decoder subunits.
  maindec md(clk, reset, op,
             pcwrite, memwrite, irwrite, regwrite,
             alusrca, branch, iord, memtoreg, regdst, 
             alusrcb, pcsrc, aluop);
  aludec  ad(funct, aluop, alucontrol);

  assign pcen = pcwrite |( branch & zero);
 
endmodule

multi_cycle/mips.v

`include "datapath.v"
`include "controller.v"
module mips(input         clk, reset,
            output  [31:0] adr, writedata,
            output         memwrite,
            input   [31:0] readdata);

  wire        zero, pcen, irwrite, regwrite,
               alusrca, iord, memtoreg, regdst;
  wire [1:0]  alusrcb, pcsrc;
  wire [2:0]  alucontrol;
  wire [5:0]  op, funct;

  controller c(clk, reset, op, funct, zero,
               pcen, memwrite, irwrite, regwrite,
               alusrca, iord, memtoreg, regdst, 
               alusrcb, pcsrc, alucontrol);
  datapath dp(clk, reset, 
              pcen, irwrite, regwrite,
              alusrca, iord, memtoreg, regdst,
              alusrcb, pcsrc, alucontrol,
              op, funct, zero,
              adr, writedata, readdata);
endmodule

multi_cycle/mipstop.v

`include "mem.v"
`include "mips.v"
module top(input 	clk, reset, 
           output [31:0] writedata, adr, 
           output      memwrite);

  wire [31:0] readdata;
  
  mips mips(clk, reset, adr, writedata, memwrite, readdata);
   
  mem mem(clk, memwrite, adr, writedata, readdata);

endmodule

multi_cycle/mipstests.v
`include "mipstop.v"
module testbench();

    reg clk;
    reg reset;

  wire [31:0] writedata, dataadr;
  wire memwrite;

  // instantiate device to be tested
  top dut(clk, reset, writedata, dataadr, memwrite);
  
  // initialize test
  initial
    begin
      $dumpfile("mips.vcd");
      $dumpvars(0,testbench);
      reset <= 1; # 22; reset <= 0;
      #300;
      $finish;
    end

  // generate clock to sequence tests
  always
    begin
      clk <= 1; # 5; clk <= 0; # 5;
    end

  // check that 7 gets written to address 84
  always@(negedge clk)
    begin
      if(memwrite) begin
        if(dataadr === 84 & writedata === 7) begin
          $display("Simulation succeeded");
          $finish;
        end else if (dataadr !== 80) begin
          $display("Simulation failed");
          $finish;
        end
      end
    end
endmodule

multi_cycle/mips.vcd
$date
	Mon Jul  6 03:10:00 2020
$end
$version
	Icarus Verilog
$end
$timescale
	1s
$end
$scope module testbench $end
$var wire 32 ! writedata [31:0] $end
$var wire 1 " memwrite $end
$var wire 32 # dataadr [31:0] $end
$var reg 1 $ clk $end
$var reg 1 % reset $end
$scope module dut $end
$var wire 1 $ clk $end
$var wire 1 % reset $end
$var wire 32 & writedata [31:0] $end
$var wire 32 ' readdata [31:0] $end
$var wire 1 " memwrite $end
$var wire 32 ( adr [31:0] $end
$scope module mem $end
$var wire 1 $ clk $end
$var wire 32 ) rd [31:0] $end
$var wire 1 " we $end
$var wire 32 * wd [31:0] $end
$var wire 32 + a [31:0] $end
$upscope $end
$scope module mips $end
$var wire 1 $ clk $end
$var wire 32 , readdata [31:0] $end
$var wire 1 % reset $end
$var wire 1 - zero $end
$var wire 32 . writedata [31:0] $end
$var wire 1 / regwrite $end
$var wire 1 0 regdst $end
$var wire 2 1 pcsrc [1:0] $end
$var wire 1 2 pcen $end
$var wire 6 3 op [5:0] $end
$var wire 1 " memwrite $end
$var wire 1 4 memtoreg $end
$var wire 1 5 irwrite $end
$var wire 1 6 iord $end
$var wire 6 7 funct [5:0] $end
$var wire 2 8 alusrcb [1:0] $end
$var wire 1 9 alusrca $end
$var wire 3 : alucontrol [2:0] $end
$var wire 32 ; adr [31:0] $end
$scope module c $end
$var wire 1 $ clk $end
$var wire 1 2 pcen $end
$var wire 1 % reset $end
$var wire 1 - zero $end
$var wire 1 / regwrite $end
$var wire 1 0 regdst $end
$var wire 1 < pcwrite $end
$var wire 2 = pcsrc [1:0] $end
$var wire 6 > op [5:0] $end
$var wire 1 " memwrite $end
$var wire 1 4 memtoreg $end
$var wire 1 5 irwrite $end
$var wire 1 6 iord $end
$var wire 6 ? funct [5:0] $end
$var wire 1 @ branch $end
$var wire 2 A alusrcb [1:0] $end
$var wire 1 9 alusrca $end
$var wire 2 B aluop [1:0] $end
$var wire 3 C alucontrol [2:0] $end
$scope module ad $end
$var wire 6 D funct [5:0] $end
$var wire 2 E aluop [1:0] $end
$var reg 3 F alucontrol [2:0] $end
$upscope $end
$scope module md $end
$var wire 1 $ clk $end
$var wire 1 % reset $end
$var wire 1 / regwrite $end
$var wire 1 0 regdst $end
$var wire 1 < pcwrite $end
$var wire 2 G pcsrc [1:0] $end
$var wire 6 H op [5:0] $end
$var wire 1 " memwrite $end
$var wire 1 4 memtoreg $end
$var wire 1 5 irwrite $end
$var wire 1 6 iord $end
$var wire 1 @ branch $end
$var wire 2 I alusrcb [1:0] $end
$var wire 1 9 alusrca $end
$var wire 2 J aluop [1:0] $end
$var reg 15 K controls [14:0] $end
$var reg 4 L nextstate [3:0] $end
$var reg 4 M state [3:0] $end
$upscope $end
$upscope $end
$scope module dp $end
$var wire 3 N alucontrol [2:0] $end
$var wire 1 9 alusrca $end
$var wire 2 O alusrcb [1:0] $end
$var wire 1 $ clk $end
$var wire 1 6 iord $end
$var wire 1 5 irwrite $end
$var wire 1 4 memtoreg $end
$var wire 1 2 pcen $end
$var wire 2 P pcsrc [1:0] $end
$var wire 32 Q readdata [31:0] $end
$var wire 1 0 regdst $end
$var wire 1 / regwrite $end
$var wire 1 % reset $end
$var wire 1 - zero $end
$var wire 5 R writereg [4:0] $end
$var wire 32 S writedata [31:0] $end
$var wire 32 T wd3 [31:0] $end
$var wire 32 U srcb [31:0] $end
$var wire 32 V srca [31:0] $end
$var wire 32 W signimmsh [31:0] $end
$var wire 32 X signimm [31:0] $end
$var wire 32 Y rd2 [31:0] $end
$var wire 32 Z rd1 [31:0] $end
$var wire 32 [ pcnext [31:0] $end
$var wire 32 \ pc [31:0] $end
$var wire 6 ] op [5:0] $end
$var wire 32 ^ instr [31:0] $end
$var wire 6 _ funct [5:0] $end
$var wire 32 ` data [31:0] $end
$var wire 32 a aluresult [31:0] $end
$var wire 32 b aluout [31:0] $end
$var wire 32 c adr [31:0] $end
$var wire 32 d a [31:0] $end
$scope module adrmux $end
$var wire 1 6 s $end
$var wire 32 e y [31:0] $end
$var wire 32 f d1 [31:0] $end
$var wire 32 g d0 [31:0] $end
$upscope $end
$scope module alu $end
$var wire 3 h aluop [2:0] $end
$var wire 32 i b [31:0] $end
$var wire 32 j a [31:0] $end
$var reg 32 k result [31:0] $end
$var reg 1 - zero $end
$upscope $end
$scope module alureg $end
$var wire 1 $ clk $end
$var wire 32 l d [31:0] $end
$var wire 1 % reset $end
$var reg 32 m q [31:0] $end
$upscope $end
$scope module areg $end
$var wire 1 $ clk $end
$var wire 1 % reset $end
$var wire 32 n d [31:0] $end
$var reg 32 o q [31:0] $end
$upscope $end
$scope module breg $end
$var wire 1 $ clk $end
$var wire 1 % reset $end
$var wire 32 p d [31:0] $end
$var reg 32 q q [31:0] $end
$upscope $end
$scope module datareg $end
$var wire 1 $ clk $end
$var wire 32 r d [31:0] $end
$var wire 1 % reset $end
$var reg 32 s q [31:0] $end
$upscope $end
$scope module immsh $end
$var wire 32 t y [31:0] $end
$var wire 32 u a [31:0] $end
$upscope $end
$scope module instrreg $end
$var wire 1 $ clk $end
$var wire 32 v d [31:0] $end
$var wire 1 5 en $end
$var wire 1 % reset $end
$var reg 32 w q [31:0] $end
$upscope $end
$scope module pcmux $end
$var wire 32 x d0 [31:0] $end
$var wire 32 y d1 [31:0] $end
$var wire 32 z d2 [31:0] $end
$var wire 2 { s [1:0] $end
$var wire 32 | y [31:0] $end
$upscope $end
$scope module pcreg $end
$var wire 1 $ clk $end
$var wire 32 } d [31:0] $end
$var wire 1 2 en $end
$var wire 1 % reset $end
$var reg 32 ~ q [31:0] $end
$upscope $end
$scope module regdstmux $end
$var wire 5 !" d0 [4:0] $end
$var wire 5 "" d1 [4:0] $end
$var wire 1 0 s $end
$var wire 5 #" y [4:0] $end
$upscope $end
$scope module rf $end
$var wire 1 $ clk $end
$var wire 5 $" ra1 [4:0] $end
$var wire 5 %" ra2 [4:0] $end
$var wire 5 &" wa3 [4:0] $end
$var wire 1 / we3 $end
$var wire 32 '" wd3 [31:0] $end
$var wire 32 (" rd2 [31:0] $end
$var wire 32 )" rd1 [31:0] $end
$upscope $end
$scope module se $end
$var wire 16 *" a [15:0] $end
$var wire 32 +" y [31:0] $end
$upscope $end
$scope module srcamux $end
$var wire 32 ," d0 [31:0] $end
$var wire 32 -" d1 [31:0] $end
$var wire 1 9 s $end
$var wire 32 ." y [31:0] $end
$upscope $end
$scope module srcbmux $end
$var wire 32 /" d0 [31:0] $end
$var wire 32 0" d1 [31:0] $end
$var wire 32 1" d2 [31:0] $end
$var wire 32 2" d3 [31:0] $end
$var wire 2 3" s [1:0] $end
$var reg 32 4" y [31:0] $end
$upscope $end
$scope module wdmux $end
$var wire 32 5" d0 [31:0] $end
$var wire 32 6" d1 [31:0] $end
$var wire 1 4 s $end
$var wire 32 7" y [31:0] $end
$upscope $end
$upscope $end
$upscope $end
$upscope $end
$upscope $end
$enddefinitions $end
#0
$dumpvars
b0 7"
b0 6"
b0 5"
b100 4"
b1 3"
b0 2"
b0 1"
b100 0"
b0 /"
b0 ."
b0 -"
b0 ,"
b0 +"
b0 *"
b0 )"
b0 ("
b0 '"
b0 &"
b0 %"
b0 $"
b0 #"
b0 ""
b0 !"
b0 ~
bx }
bx |
b0 {
b0 z
b0 y
b100 x
b0 w
b100000000000100000000000000101 v
b0 u
b0 t
b0 s
b100000000000100000000000000101 r
b0 q
b0 p
b0 o
b0 n
b0 m
b100 l
b100 k
b0 j
b100 i
b10 h
b0 g
b0 f
b0 e
b0 d
b0 c
b0 b
b100 a
b0 `
b0 _
b0 ^
b0 ]
b0 \
bx [
b0 Z
b0 Y
b0 X
b0 W
b0 V
b100 U
b0 T
b0 S
b0 R
b100000000000100000000000000101 Q
b0 P
b1 O
b10 N
b0 M
b1 L
b101000000010000 K
b0 J
b1 I
b0 H
b0 G
b10 F
b0 E
b0 D
b10 C
b0 B
b1 A
0@
b0 ?
b0 >
b0 =
1<
b0 ;
b10 :
09
b1 8
b0 7
06
15
04
b0 3
12
b0 1
00
0/
b0 .
0-
b100000000000100000000000000101 ,
b0 +
b0 *
b100000000000100000000000000101 )
b0 (
b100000000000100000000000000101 '
b0 &
1%
1$
b0 #
0"
b0 !
$end
#1
b100 [
b100 |
b100 }
#5
0$
#10
1$
#15
0$
#20
1$
#22
0%
#25
0$
#30
b10100 U
b10100 i
b10100 4"
02
0<
05
b11 8
b11 A
b11 I
b11 O
b11 3"
b11000 a
b11000 k
b11000 l
b11000 x
b110000 K
b1001 L
b10100 W
b10100 t
b10100 2"
bx Y
bx p
bx ("
b10 R
b10 #"
b10 &"
b100000000000110000000000001100 '
b100000000000110000000000001100 )
b100000000000110000000000001100 ,
b100000000000110000000000001100 Q
b100000000000110000000000001100 r
b100000000000110000000000001100 v
b100 T
b100 '"
b100 7"
b10000000000000010100 z
b101 X
b101 u
b101 +"
b101 1"
b101 *"
b10 %"
b10 !"
b101 7
b101 ?
b101 D
b101 _
b1000 3
b1000 >
b1000 H
b1000 ]
b100 V
b100 j
b100 ."
b100 #
b100 (
b100 +
b100 ;
b100 c
b100 e
b100 b
b100 f
b100 m
b100 y
b100 5"
b100000000000100000000000000101 `
b100000000000100000000000000101 s
b100000000000100000000000000101 6"
b100000000000100000000000000101 ^
b100000000000100000000000000101 w
b100 \
b100 g
b100 ~
b100 ,"
b1 M
1$
#31
b11000 [
b11000 |
b11000 }
#35
0$
#40
b101 a
b101 k
b101 l
b101 x
b101 U
b101 i
b101 4"
b0 V
b0 j
b0 ."
19
b10 8
b10 A
b10 I
b10 O
b10 3"
b10000100000 K
b1010 L
b11000 T
b11000 '"
b11000 7"
b1001 M
b100000000000110000000000001100 `
b100000000000110000000000001100 s
b100000000000110000000000001100 6"
bx !
bx &
bx *
bx .
bx S
bx q
bx /"
b11000 b
b11000 f
b11000 m
b11000 y
b11000 5"
1$
#41
b101 [
b101 |
b101 }
#45
0$
#50
bx a
bx k
bx l
bx x
bx U
bx i
bx 4"
b100 V
b100 j
b100 ."
1/
09
b0 8
b0 A
b0 I
b0 O
b0 3"
b100000000000 K
b0 L
b101 T
b101 '"
b101 7"
b101 b
b101 f
b101 m
b101 y
b101 5"
b1010 M
1$
#51
bx [
bx |
bx }
#55
0$
#60
b1000 a
b1000 k
b1000 l
b1000 x
b100 U
b100 i
b100 4"
12
1<
15
0/
b1 8
b1 A
b1 I
b1 O
b1 3"
b101000000010000 K
b1 L
b101 Y
b101 p
b101 ("
bx T
bx '"
bx 7"
b0 M
bx b
bx f
bx m
bx y
bx 5"
1$
#61
b1000 [
b1000 |
b1000 }
#65
0$
#70
b110000 U
b110000 i
b110000 4"
02
0<
05
b11 8
b11 A
b11 I
b11 O
b11 3"
b111000 a
b111000 k
b111000 l
b111000 x
b110000 K
b1001 L
b110000 W
b110000 t
b110000 2"
bx Y
bx p
bx ("
b11 R
b11 #"
b11 &"
b100000011001111111111111110111 '
b100000011001111111111111110111 )
b100000011001111111111111110111 ,
b100000011001111111111111110111 Q
b100000011001111111111111110111 r
b100000011001111111111111110111 v
b1000 T
b1000 '"
b1000 7"
b11000000000000110000 z
b1100 X
b1100 u
b1100 +"
b1100 1"
b1100 *"
b11 %"
b11 !"
b1100 7
b1100 ?
b1100 D
b1100 _
b1000 V
b1000 j
b1000 ."
b1000 #
b1000 (
b1000 +
b1000 ;
b1000 c
b1000 e
b1000 b
b1000 f
b1000 m
b1000 y
b1000 5"
b101 !
b101 &
b101 *
b101 .
b101 S
b101 q
b101 /"
b100000000000110000000000001100 ^
b100000000000110000000000001100 w
b1000 \
b1000 g
b1000 ~
b1000 ,"
b1 M
1$
#71
b111000 [
b111000 |
b111000 }
#75
0$
#80
b1100 a
b1100 k
b1100 l
b1100 x
b1100 U
b1100 i
b1100 4"
b0 V
b0 j
b0 ."
19
b10 8
b10 A
b10 I
b10 O
b10 3"
b10000100000 K
b1010 L
b111000 T
b111000 '"
b111000 7"
b1001 M
b100000011001111111111111110111 `
b100000011001111111111111110111 s
b100000011001111111111111110111 6"
bx !
bx &
bx *
bx .
bx S
bx q
bx /"
b111000 b
b111000 f
b111000 m
b111000 y
b111000 5"
1$
#81
b1100 [
b1100 |
b1100 }
#85
0$
#90
bx a
bx k
bx l
bx x
bx U
bx i
bx 4"
b1000 V
b1000 j
b1000 ."
1/
09
b0 8
b0 A
b0 I
b0 O
b0 3"
b100000000000 K
b0 L
b1100 T
b1100 '"
b1100 7"
b1100 b
b1100 f
b1100 m
b1100 y
b1100 5"
b1010 M
1$
#91
bx [
bx |
bx }
#95
0$
#100
b1100 a
b1100 k
b1100 l
b1100 x
b100 U
b100 i
b100 4"
12
1<
15
0/
b1 8
b1 A
b1 I
b1 O
b1 3"
b101000000010000 K
b1 L
b1100 Y
b1100 p
b1100 ("
bx T
bx '"
bx 7"
b0 M
bx b
bx f
bx m
bx y
bx 5"
1$
#101
b1100 [
b1100 |
b1100 }
#105
0$
#110
b11111111111111111111111111011100 U
b11111111111111111111111111011100 i
b11111111111111111111111111011100 4"
02
0<
05
b11 8
b11 A
b11 I
b11 O
b11 3"
b11111111111111111111111111101000 a
b11111111111111111111111111101000 k
b11111111111111111111111111101000 l
b11111111111111111111111111101000 x
b110000 K
b1001 L
b11111111111111111111111111011100 W
b11111111111111111111111111011100 t
b11111111111111111111111111011100 2"
bx Y
bx p
bx ("
b1100 Z
b1100 n
b1100 )"
b111 R
b111 #"
b111 &"
b111000100010000000100101 '
b111000100010000000100101 )
b111000100010000000100101 ,
b111000100010000000100101 Q
b111000100010000000100101 r
b111000100010000000100101 v
b1100 T
b1100 '"
b1100 7"
b1100111111111111111011100 z
b11111111111111111111111111110111 X
b11111111111111111111111111110111 u
b11111111111111111111111111110111 +"
b11111111111111111111111111110111 1"
b1111111111110111 *"
b111 %"
b11 $"
b11111 ""
b111 !"
b110111 7
b110111 ?
b110111 D
b110111 _
b1100 V
b1100 j
b1100 ."
b1100 #
b1100 (
b1100 +
b1100 ;
b1100 c
b1100 e
b1100 b
b1100 f
b1100 m
b1100 y
b1100 5"
b1100 !
b1100 &
b1100 *
b1100 .
b1100 S
b1100 q
b1100 /"
b100000011001111111111111110111 ^
b100000011001111111111111110111 w
b1100 \
b1100 g
b1100 ~
b1100 ,"
b1 M
1$
#111
b11111111111111111111111111101000 [
b11111111111111111111111111101000 |
b11111111111111111111111111101000 }
#115
0$
#120
b11 a
b11 k
b11 l
b11 x
b11111111111111111111111111110111 U
b11111111111111111111111111110111 i
b11111111111111111111111111110111 4"
19
b10 8
b10 A
b10 I
b10 O
b10 3"
b10000100000 K
b1010 L
b11111111111111111111111111101000 T
b11111111111111111111111111101000 '"
b11111111111111111111111111101000 7"
b1001 M
b111000100010000000100101 `
b111000100010000000100101 s
b111000100010000000100101 6"
b1100 d
b1100 o
b1100 -"
bx !
bx &
bx *
bx .
bx S
bx q
bx /"
b11111111111111111111111111101000 b
b11111111111111111111111111101000 f
b11111111111111111111111111101000 m
b11111111111111111111111111101000 y
b11111111111111111111111111101000 5"
1$
#121
b11 [
b11 |
b11 }
#125
0$
#130
bx a
bx k
bx l
bx x
bx U
bx i
bx 4"
1/
09
b0 8
b0 A
b0 I
b0 O
b0 3"
b100000000000 K
b0 L
b11 T
b11 '"
b11 7"
b11 b
b11 f
b11 m
b11 y
b11 5"
b1010 M
1$
#131
bx [
bx |
bx }
#135
0$
#140
b10000 a
b10000 k
b10000 l
b10000 x
b100 U
b100 i
b100 4"
12
1<
15
0/
b1 8
b1 A
b1 I
b1 O
b1 3"
b101000000010000 K
b1 L
b11 Y
b11 p
b11 ("
bx T
bx '"
bx 7"
b0 M
bx b
bx f
bx m
bx y
bx 5"
1$
#141
b10000 [
b10000 |
b10000 }
#145
0$
#150
b1000000010010100 U
b1000000010010100 i
b1000000010010100 4"
02
0<
05
b11 8
b11 A
b11 I
b11 O
b11 3"
b1000000010100100 a
b1000000010100100 k
b1000000010100100 l
b1000000010100100 x
b110000 K
b110 L
b1000000010010100 W
b1000000010010100 t
b1000000010010100 2"
b101 Y
b101 p
b101 ("
b11 Z
b11 n
b11 )"
b10 R
b10 #"
b10 &"
b11001000010100000100100 '
b11001000010100000100100 )
b11001000010100000100100 ,
b11001000010100000100100 Q
b11001000010100000100100 r
b11001000010100000100100 v
b10000 T
b10000 '"
b10000 7"
b11100010001000000010010100 z
b10000000100101 X
b10000000100101 u
b10000000100101 +"
b10000000100101 1"
b10000000100101 *"
b10 %"
b111 $"
b100 ""
b10 !"
b100101 7
b100101 ?
b100101 D
b100101 _
b0 3
b0 >
b0 H
b0 ]
b10000 V
b10000 j
b10000 ."
b10000 #
b10000 (
b10000 +
b10000 ;
b10000 c
b10000 e
b10000 b
b10000 f
b10000 m
b10000 y
b10000 5"
b11 !
b11 &
b11 *
b11 .
b11 S
b11 q
b11 /"
b111000100010000000100101 ^
b111000100010000000100101 w
b10000 \
b10000 g
b10000 ~
b10000 ,"
b1 M
1$
#151
b1000000010100100 [
b1000000010100100 |
b1000000010100100 }
#155
0$
#160
b111 a
b111 k
b111 l
b111 x
b101 U
b101 i
b101 4"
b1 :
b1 C
b1 F
b1 N
b1 h
b11 V
b11 j
b11 ."
19
b0 8
b0 A
b0 I
b0 O
b0 3"
b10 B
b10 E
b10 J
b10000000010 K
b111 L
b1000000010100100 T
b1000000010100100 '"
b1000000010100100 7"
b110 M
b11001000010100000100100 `
b11001000010100000100100 s
b11001000010100000100100 6"
b11 d
b11 o
b11 -"
b101 !
b101 &
b101 *
b101 .
b101 S
b101 q
b101 /"
b1000000010100100 b
b1000000010100100 f
b1000000010100100 m
b1000000010100100 y
b1000000010100100 5"
1$
#161
b111 [
b111 |
b111 }
